pullbot/__init__.py
pullbot/_version.py
pullbot/auth.py
pullbot/pullbot.py
pullbot/util.py
pullbot-0.1.2.dist-info/DESCRIPTION.rst
pullbot-0.1.2.dist-info/METADATA
pullbot-0.1.2.dist-info/RECORD
pullbot-0.1.2.dist-info/WHEEL
pullbot-0.1.2.dist-info/entry_points.txt
pullbot-0.1.2.dist-info/metadata.json
pullbot-0.1.2.dist-info/top_level.txt
pullbot-0.1.2.dist-info/zip-safe
tests/unit/__init__.py
