Metadata-Version: 2.0
Name: pullbot
Version: 0.1.2
Summary: GitHub PR automation
Home-page: https://github.com/greenape/pullbot
Author: Jonathan Gray
Author-email: jono@nanosheep.net
License: GPLv3
Keywords: github automation bots
Platform: MacOS X
Platform: Linux
Classifier: Development Status :: 4 - Beta
Classifier: Intended Audience :: Developers
Classifier: License :: Other/Proprietary License
Classifier: Programming Language :: Python :: 3.4
Classifier: Programming Language :: Python :: 3.5
Classifier: Natural Language :: English
Classifier: Operating System :: MacOS :: MacOS X
Classifier: Operating System :: POSIX
Classifier: Operating System :: POSIX :: Linux
Requires-Dist: github3.py (>=1.0.0a4)
